grundkurs_theme/__init__.py
grundkurs_theme/_version.py
grundkurs_theme/handlers.py
grundkurs_theme-1.1.0.data/data/etc/jupyter/jupyter_notebook_config.d/grundkurs_theme.json
grundkurs_theme-1.1.0.data/data/etc/jupyter/jupyter_server_config.d/grundkurs_theme.json
grundkurs_theme-1.1.0.data/data/share/jupyter/labextensions/grundkurs_theme/package.json
grundkurs_theme-1.1.0.data/data/share/jupyter/labextensions/grundkurs_theme/schemas/grundkurs_theme/package.json.orig
grundkurs_theme-1.1.0.data/data/share/jupyter/labextensions/grundkurs_theme/schemas/grundkurs_theme/plugin.json
grundkurs_theme-1.1.0.data/data/share/jupyter/labextensions/grundkurs_theme/static/525.e0fe8d4ae003c5ab3c17.js
grundkurs_theme-1.1.0.data/data/share/jupyter/labextensions/grundkurs_theme/static/remoteEntry.9a51162551b2d2d76f7b.js
grundkurs_theme-1.1.0.data/data/share/jupyter/labextensions/grundkurs_theme/static/style.js
grundkurs_theme-1.1.0.data/data/share/jupyter/labextensions/grundkurs_theme/static/third-party-licenses.json
grundkurs_theme-1.1.0.data/data/share/jupyter/labextensions/grundkurs_theme/themes/grundkurs_theme/index.css
grundkurs_theme-1.1.0.data/data/share/jupyter/labextensions/grundkurs_theme/themes/grundkurs_theme/index.js
grundkurs_theme-1.1.0.data/data/share/jupyter/labextensions/grundkurs_theme/install.json
grundkurs_theme-1.1.0.dist-info/METADATA
grundkurs_theme-1.1.0.dist-info/WHEEL
grundkurs_theme-1.1.0.dist-info/licenses/LICENSE
grundkurs_theme-1.1.0.dist-info/RECORD
